{
  "stats": {
    "suites": 2,
    "tests": 10,
    "passes": 9,
    "pending": 0,
    "failures": 1,
    "start": "2022-04-21T07:08:59.682Z",
    "end": "2022-04-21T07:09:06.772Z",
    "duration": 5541,
    "testsRegistered": 10,
    "passPercent": 90,
    "pendingPercent": 0,
    "other": 0,
    "hasOther": false,
    "skipped": 0,
    "hasSkipped": false
  },
  "results": [
    {
      "uuid": "49f722c2-5fff-4f52-b26c-5c543ab52221",
      "title": "",
      "fullFile": "cypress/integration/TC01_login.test.js",
      "file": "cypress/integration/TC01_login.test.js",
      "beforeHooks": [],
      "afterHooks": [],
      "tests": [],
      "suites": [
        {
          "uuid": "dabf785e-01d8-411e-aec5-7611bf2ec057",
          "title": "as a user, i want to login successfully",
          "fullFile": "",
          "file": "",
          "beforeHooks": [],
          "afterHooks": [],
          "tests": [],
          "suites": [
            {
              "uuid": "3f6e6e41-c481-4b32-a63a-e64933dedba4",
              "title": "User Login using Invalid Credential",
              "fullFile": "",
              "file": "",
              "beforeHooks": [],
              "afterHooks": [],
              "tests": [
                {
                  "title": "user filled in username",
                  "fullTitle": "as a user, i want to login successfully User Login using Invalid Credential user filled in username",
                  "timedOut": null,
                  "duration": 1175,
                  "state": "passed",
                  "speed": "fast",
                  "pass": true,
                  "fail": false,
                  "pending": false,
                  "context": null,
                  "code": "_login.default.setUsername(data.username);",
                  "err": {},
                  "uuid": "51e70f80-6501-4d57-b83f-c89b120ecd81",
                  "parentUUID": "3f6e6e41-c481-4b32-a63a-e64933dedba4",
                  "isHook": false,
                  "skipped": false
                },
                {
                  "title": "user filled in password",
                  "fullTitle": "as a user, i want to login successfully User Login using Invalid Credential user filled in password",
                  "timedOut": null,
                  "duration": 409,
                  "state": "passed",
                  "speed": "fast",
                  "pass": true,
                  "fail": false,
                  "pending": false,
                  "context": null,
                  "code": "_login.default.setPassword(data.password);",
                  "err": {},
                  "uuid": "3da1ee36-c422-4ae2-a9b6-ba3d9a36e9ff",
                  "parentUUID": "3f6e6e41-c481-4b32-a63a-e64933dedba4",
                  "isHook": false,
                  "skipped": false
                },
                {
                  "title": "user tap login button",
                  "fullTitle": "as a user, i want to login successfully User Login using Invalid Credential user tap login button",
                  "timedOut": null,
                  "duration": 403,
                  "state": "passed",
                  "speed": "fast",
                  "pass": true,
                  "fail": false,
                  "pending": false,
                  "context": null,
                  "code": "_login.default.clickLogin();",
                  "err": {},
                  "uuid": "5eb1c1da-4349-41e9-b10e-4250ac1725eb",
                  "parentUUID": "3f6e6e41-c481-4b32-a63a-e64933dedba4",
                  "isHook": false,
                  "skipped": false
                }
              ],
              "suites": [],
              "passes": [
                "51e70f80-6501-4d57-b83f-c89b120ecd81",
                "3da1ee36-c422-4ae2-a9b6-ba3d9a36e9ff",
                "5eb1c1da-4349-41e9-b10e-4250ac1725eb"
              ],
              "failures": [],
              "pending": [],
              "skipped": [],
              "duration": 1987,
              "root": false,
              "rootEmpty": false,
              "_timeout": 2000
            },
            {
              "uuid": "c38b44a0-9b59-443d-af4c-7187b67d0d42",
              "title": "User login using Invalid Credential",
              "fullFile": "",
              "file": "",
              "beforeHooks": [],
              "afterHooks": [],
              "tests": [
                {
                  "title": "user filled in username",
                  "fullTitle": "as a user, i want to login successfully User login using Invalid Credential user filled in username",
                  "timedOut": null,
                  "duration": 293,
                  "state": "passed",
                  "speed": "fast",
                  "pass": true,
                  "fail": false,
                  "pending": false,
                  "context": null,
                  "code": "_login.default.setUsername(data.username);",
                  "err": {},
                  "uuid": "2b684466-6573-4cdf-9133-256abe8a29bd",
                  "parentUUID": "c38b44a0-9b59-443d-af4c-7187b67d0d42",
                  "isHook": false,
                  "skipped": false
                },
                {
                  "title": "user filled in password",
                  "fullTitle": "as a user, i want to login successfully User login using Invalid Credential user filled in password",
                  "timedOut": null,
                  "duration": 321,
                  "state": "passed",
                  "speed": "fast",
                  "pass": true,
                  "fail": false,
                  "pending": false,
                  "context": null,
                  "code": "_login.default.setPassword(data.password);",
                  "err": {},
                  "uuid": "42ecc67c-042e-4895-8d55-e1da2886694e",
                  "parentUUID": "c38b44a0-9b59-443d-af4c-7187b67d0d42",
                  "isHook": false,
                  "skipped": false
                },
                {
                  "title": "user tap login button",
                  "fullTitle": "as a user, i want to login successfully User login using Invalid Credential user tap login button",
                  "timedOut": null,
                  "duration": 524,
                  "state": "passed",
                  "speed": "fast",
                  "pass": true,
                  "fail": false,
                  "pending": false,
                  "context": null,
                  "code": "_login.default.clickLogin();",
                  "err": {},
                  "uuid": "8cf7b496-41d8-4911-aeaf-2d258eb633b1",
                  "parentUUID": "c38b44a0-9b59-443d-af4c-7187b67d0d42",
                  "isHook": false,
                  "skipped": false
                }
              ],
              "suites": [],
              "passes": [
                "2b684466-6573-4cdf-9133-256abe8a29bd",
                "42ecc67c-042e-4895-8d55-e1da2886694e",
                "8cf7b496-41d8-4911-aeaf-2d258eb633b1"
              ],
              "failures": [],
              "pending": [],
              "skipped": [],
              "duration": 1138,
              "root": false,
              "rootEmpty": false,
              "_timeout": 2000
            }
          ],
          "passes": [],
          "failures": [],
          "pending": [],
          "skipped": [],
          "duration": 0,
          "root": false,
          "rootEmpty": false,
          "_timeout": 2000
        }
      ],
      "passes": [],
      "failures": [],
      "pending": [],
      "skipped": [],
      "duration": 0,
      "root": true,
      "rootEmpty": true,
      "_timeout": 2000
    },
    {
      "uuid": "24cb336b-bccb-406a-9657-cf98cc10884f",
      "title": "",
      "fullFile": "cypress/integration/TC02_FailedCase.test.js",
      "file": "cypress/integration/TC02_FailedCase.test.js",
      "beforeHooks": [],
      "afterHooks": [],
      "tests": [],
      "suites": [
        {
          "uuid": "63586f56-d340-428a-97da-d18ffdd1dfbb",
          "title": "this for scenario failed case and uploaded image",
          "fullFile": "",
          "file": "",
          "beforeHooks": [],
          "afterHooks": [],
          "tests": [],
          "suites": [
            {
              "uuid": "f347a386-1899-4a3e-a41d-26f85594a7a3",
              "title": "Wording Message Invalid Login",
              "fullFile": "",
              "file": "",
              "beforeHooks": [],
              "afterHooks": [],
              "tests": [
                {
                  "title": "user filled in username",
                  "fullTitle": "this for scenario failed case and uploaded image Wording Message Invalid Login user filled in username",
                  "timedOut": null,
                  "duration": 1325,
                  "state": "passed",
                  "speed": "fast",
                  "pass": true,
                  "fail": false,
                  "pending": false,
                  "context": null,
                  "code": "_login.default.setUsername('Admin');",
                  "err": {},
                  "uuid": "703f8d0f-3d6c-48eb-8bad-5b71c82ebe62",
                  "parentUUID": "f347a386-1899-4a3e-a41d-26f85594a7a3",
                  "isHook": false,
                  "skipped": false
                },
                {
                  "title": "user filled in wrong password",
                  "fullTitle": "this for scenario failed case and uploaded image Wording Message Invalid Login user filled in wrong password",
                  "timedOut": null,
                  "duration": 316,
                  "state": "passed",
                  "speed": "fast",
                  "pass": true,
                  "fail": false,
                  "pending": false,
                  "context": null,
                  "code": "_login.default.setPassword('!@£!$@£');",
                  "err": {},
                  "uuid": "a014d2f1-972a-4fec-8cd9-6b364adcba39",
                  "parentUUID": "f347a386-1899-4a3e-a41d-26f85594a7a3",
                  "isHook": false,
                  "skipped": false
                },
                {
                  "title": "user tap login button",
                  "fullTitle": "this for scenario failed case and uploaded image Wording Message Invalid Login user tap login button",
                  "timedOut": null,
                  "duration": 527,
                  "state": "passed",
                  "speed": "fast",
                  "pass": true,
                  "fail": false,
                  "pending": false,
                  "context": null,
                  "code": "_login.default.clickLogin();",
                  "err": {},
                  "uuid": "9cfabcbc-1f65-4d21-b4c5-94aaac4aedb2",
                  "parentUUID": "f347a386-1899-4a3e-a41d-26f85594a7a3",
                  "isHook": false,
                  "skipped": false
                },
                {
                  "title": "user verify a wording message",
                  "fullTitle": "this for scenario failed case and uploaded image Wording Message Invalid Login user verify a wording message",
                  "timedOut": null,
                  "duration": 248,
                  "state": "failed",
                  "speed": null,
                  "pass": false,
                  "fail": true,
                  "pending": false,
                  "context": "\"/__w/cypress_project/cypress_project/cypress/reports/mochareport/assets/TC02_FailedCase.test.js/Wording Message Invalid Login -- user verify a wording message (failed).png\"",
                  "code": "_login.default.wordingMessage();",
                  "err": {
                    "message": "AssertionError: expected 'Csrf token validation failed' to deeply equal 'credentials'",
                    "estack": "AssertionError: expected 'Csrf token validation failed' to deeply equal 'credentials'\n    at Context.eval (https://opensource-demo.orangehrmlive.com/__cypress/tests?p=cypress/integration/TC02_FailedCase.test.js:179:26)",
                    "diff": "- 'Csrf token validation failed'\n+ 'credentials'\n"
                  },
                  "uuid": "623c5ac2-64ec-4b7e-9802-7cdd0d6b33eb",
                  "parentUUID": "f347a386-1899-4a3e-a41d-26f85594a7a3",
                  "isHook": false,
                  "skipped": false
                }
              ],
              "suites": [],
              "passes": [
                "703f8d0f-3d6c-48eb-8bad-5b71c82ebe62",
                "a014d2f1-972a-4fec-8cd9-6b364adcba39",
                "9cfabcbc-1f65-4d21-b4c5-94aaac4aedb2"
              ],
              "failures": [
                "623c5ac2-64ec-4b7e-9802-7cdd0d6b33eb"
              ],
              "pending": [],
              "skipped": [],
              "duration": 2416,
              "root": false,
              "rootEmpty": false,
              "_timeout": 2000
            }
          ],
          "passes": [],
          "failures": [],
          "pending": [],
          "skipped": [],
          "duration": 0,
          "root": false,
          "rootEmpty": false,
          "_timeout": 2000
        }
      ],
      "passes": [],
      "failures": [],
      "pending": [],
      "skipped": [],
      "duration": 0,
      "root": true,
      "rootEmpty": true,
      "_timeout": 2000
    }
  ],
  "meta": {
    "mocha": {
      "version": "7.0.1"
    },
    "mochawesome": {
      "options": {
        "quiet": false,
        "reportFilename": "mochawesome",
        "saveHtml": true,
        "saveJson": true,
        "consoleReporter": "spec",
        "useInlineDiffs": false,
        "code": true
      },
      "version": "7.1.3"
    },
    "marge": {
      "options": {
        "id": "default",
        "reportDir": "cypress/reports/mocha",
        "quite": true,
        "overwrite": false,
        "html": true,
        "json": true,
        "showPassed": true,
        "autoOpen": false,
        "charts": true,
        "code": true
      },
      "version": "6.2.0"
    }
  }
}